[
  {
    "name": "unknown",
    "expression": "neutral",
    "age": 19.147275924682617,
    "gender": "male",
    "date": "2024-03-09",
    "time": "23:13:41",
    "path": "unknown-1710000821222.png",
    "greeting": "วันนี้อากาศดีจังเลยนะ"
  },
  {
    "name": "unknown",
    "expression": "neutral",
    "age": 18.08588218688965,
    "gender": "male",
    "date": "2024-03-09",
    "time": "23:13:52",
    "path": "unknown-1710000832339.png",
    "greeting": "วันนี้อากาศดีจังเลยนะ"
  },
  {
    "name": "unknown",
    "expression": "neutral",
    "age": 30.293073654174805,
    "gender": "male",
    "date": "2024-03-09",
    "time": "23:14:11",
    "path": "unknown-1710000851249.png",
    "greeting": "วันนี้อากาศดีจังเลยนะ"
  },
  {
    "name": "unknown",
    "expression": "happy",
    "age": 28.370149612426758,
    "gender": "male",
    "date": "2024-03-09",
    "time": "23:14:32",
    "path": "unknown-1710000872213.png",
    "greeting": "ดูท่าทางจะอารมณ์ดีนะเนี้ย"
  }
]